CHANGES.txt
CONTRIBUTORS.txt
MANIFEST.in
README.txt
setup.cfg
setup.py
Products/__init__.py
Products.mediaOrganization.egg-info/PKG-INFO
Products.mediaOrganization.egg-info/SOURCES.txt
Products.mediaOrganization.egg-info/dependency_links.txt
Products.mediaOrganization.egg-info/entry_points.txt
Products.mediaOrganization.egg-info/namespace_packages.txt
Products.mediaOrganization.egg-info/not-zip-safe
Products.mediaOrganization.egg-info/paster_plugins.txt
Products.mediaOrganization.egg-info/requires.txt
Products.mediaOrganization.egg-info/top_level.txt
Products/mediaOrganization/README.txt
Products/mediaOrganization/__init__.py
Products/mediaOrganization/config.py
Products/mediaOrganization/configure.zcml
Products/mediaOrganization/browser/__init__.py
Products/mediaOrganization/browser/configure.zcml
Products/mediaOrganization/content/__init__.py
Products/mediaOrganization/content/configure.zcml
Products/mediaOrganization/content/mediaorganization.py
Products/mediaOrganization/interfaces/__init__.py
Products/mediaOrganization/interfaces/mediaorganization.py
Products/mediaOrganization/portlets/__init__.py
Products/mediaOrganization/portlets/configure.zcml
Products/mediaOrganization/profiles/default/factorytool.xml
Products/mediaOrganization/profiles/default/metadata.xml
Products/mediaOrganization/profiles/default/portlets.xml
Products/mediaOrganization/profiles/default/rolemap.xml
Products/mediaOrganization/profiles/default/types.xml
Products/mediaOrganization/profiles/default/types/Media_Organization.xml
Products/mediaOrganization/tests/__init__.py
Products/mediaOrganization/tests/base.py
Products/mediaOrganization/tests/test_doctest.py
docs/HISTORY.txt
docs/INSTALL.txt
docs/LICENSE.GPL
docs/LICENSE.txt