Metadata-Version: 1.0
Name: Products.mediaOrganization
Version: 0.2
Summary: Organization type with folderish behaviour to hold related media.
Home-page: http://svn.plone.org/svn/collective/
Author: David Jonas
Author-email: david@intk.com
License: GPL
Keywords: type folderish organization media
Platform: UNKNOWN
Classifier: Framework :: Plone
Classifier: Intended Audience :: Developers
Classifier: License :: OSI Approved :: GNU General Public License (GPL)
